boardgg/__init__.py
boardgg/tests/__init__.py
boardgg/tests/mocks/__init__.py
boardgg/tests/mocks/boardgames.py
boardgg/tests/test_boardgames.py
boardgg/v1/__init__.py
boardgg/v1/client.py
boardgg/v1/entities.py
boardgg-0.1.0rc0.dist-info/WHEEL
boardgg-0.1.0rc0.dist-info/METADATA
boardgg-0.1.0rc0.dist-info/RECORD
