Metadata-Version: 2.1
Name: boardgg
Version: 0.1.0rc0
Summary: 
Author: Pablo Moreno
Author-email: pablomoreno.inf@gmail.com
Requires-Python: >=3.10,<4.0
Classifier: Programming Language :: Python :: 3
Classifier: Programming Language :: Python :: 3.10
Requires-Dist: requests (>=2.28.0,<3.0.0)
Requires-Dist: xmltodict (>=0.13.0,<0.14.0)
